generator/__init__.py
generator/generator.py
structure_generator_by_xakepanonim-0.3.0.dist-info/METADATA
structure_generator_by_xakepanonim-0.3.0.dist-info/WHEEL
structure_generator_by_xakepanonim-0.3.0.dist-info/entry_points.txt
structure_generator_by_xakepanonim-0.3.0.dist-info/top_level.txt
structure_generator_by_xakepanonim-0.3.0.dist-info/RECORD
