Metadata-Version: 2.1
Name: structure-generator-by-xakepanonim
Version: 0.3.0
Summary: This package automatically generates a project architecture description and saves it in the README.md file.
Home-page: https://github.com/XakepAnonim/structure_generator
Author: XakepAnonim
Classifier: Programming Language :: Python :: 3
Classifier: License :: OSI Approved :: MIT License
Classifier: Operating System :: OS Independent
Requires-Python: >=3.6
Requires-Dist: toml >=0.10.0
